fRAGme/__init__.py
fRAGme/app.py
fRAGme/api/__init__.py
fRAGme/api/v1/__init__.py
fRAGme/api/v1/auth.py
fRAGme/api/v1/cmd.py
fRAGme/api/v1/data.py
fRAGme/models/__init__.py
fRAGme/models/v1/__init__.py
fRAGme/models/v1/auth.py
fRAGme/models/v1/cmd.py
fRAGme/models/v1/data.py
fRAGme/util/__init__.py
fRAGme/util/v1/__init__.py
fRAGme/util/v1/auth.py
fRAGme/util/v1/chroma_handler.py
fragme-0.1.10.dist-info/LICENSE
fragme-0.1.10.dist-info/WHEEL
fragme-0.1.10.dist-info/METADATA
fragme-0.1.10.dist-info/RECORD
